jamjam/__init__.py
jamjam/_testing.py
jamjam/_text.py
jamjam/c.py
jamjam/classes.py
jamjam/funcs.py
jamjam/iter.py
jamjam/py.typed
jamjam/typing.py
jamjam/win.py
jamjam/winapi.py
jamjam/_scripts/__init__.py
jamjam/_scripts/dark.py
jamjam/_scripts/idle.py
jamjam/_scripts/info.py
jamjam-0.0.3.dist-info/licenses/LICENSE
jamjam-0.0.3.dist-info/METADATA
jamjam-0.0.3.dist-info/WHEEL
jamjam-0.0.3.dist-info/entry_points.txt
jamjam-0.0.3.dist-info/top_level.txt
jamjam-0.0.3.dist-info/RECORD
