Metadata-Version: 2.4
Name: jamjam
Version: 0.0.3
License-Expression: GPL-3.0
Requires-Python: >=3.11
License-File: LICENSE
Requires-Dist: typing_extensions>=4.12.0
Provides-Extra: dev
Requires-Dist: mypy; extra == "dev"
Requires-Dist: pre-commit; extra == "dev"
Requires-Dist: pytest; extra == "dev"
Requires-Dist: sphinx; extra == "dev"
Requires-Dist: furo; extra == "dev"
Dynamic: license-file
